{
    "title": "PA Merchandise for Charity! T-shirts, Mugs, and More! - Doctors without Borders",
    "description": "Check out my new store!  You can represent the Knights of Apollo and support Doctors without borders!  100% of the proceeds will go to charity!\n\nStore: https:\/\/teespring.com\/stores\/pixelated-apollo\n\nDoctors without Borders: https:\/\/donate.doctorswithoutborders.org\/onetime-b.cfm?source=ADD170U0U01&utm_source=AdWords&utm_medium=ppc&utm_campaign=GooglePaid&utm_content=brand\n\nIf you enjoyed the video don't forget to Like and Leave a comment :D\n\n-----------------------------------------PA Merchandise----------------------------------------------\n\nBUYING A SHIRT WILL SUPPORT A CHARITY!\n\nRepresent the Knight's of Apollo!\nBuy a T-shirt Here: Coming Soon!\n\n----------------------------------How You Can Support Me! -----------------------------------\n\n- Like, share and leave a comment :D\n- Turn OFF adblock or whitelist my channel\n- Send me a GREAT battle Replay: pixelatedapollo@gmail.com\n\n------------------------------------------Connect With Me!-----------------------------------------\n\n- Email: pixelatedapollo@gmail.com\n- Twitter: https:\/\/twitter.com\/PixelatedApollo\n- Steam Group:  http:\/\/steamcommunity.com\/groups\/apollosknights\n- Twitch: http:\/\/www.twitch.tv\/pixelatedapollo",
    "referenceId": "1eJK9AF-ib4",
    "date_created": "1491525061",
    "date_modified": "1506478188",
    "tags": "",
    "sourceId": "4",
    "status": "approved",
    "visibility": "1",
    "VV_VI": null,
    "engagement_score": null,
    "conversion_score": null,
    "CVV_VI": null,
    "id": "117404894",
    "loginId": "1759034",
    "entityType": "1",
    "titleTextEncoded": "PA-Merchandise-for-Charity-T-shirts-Mugs-and-More-Doctors-without-Borders",
    "category": "",
    "tvp_profiles": [
        "32",
        "25"
    ],
    "tvp_profiles_manual": "",
    "tvp_profiles_maxscore": 968.5233,
    "VIDEO_LENGTH": "LONG",
    "duration": 369,
    "settings": "",
    "asset": {
        "type": "youtube",
        "thumbnailUrl": "https:\/\/i.ytimg.com\/vi\/1eJK9AF-ib4\/maxresdefault.jpg",
        "uploadDate": 1491525061,
        "videoId": "1eJK9AF-ib4",
        "title": "PA Merchandise for Charity! T-shirts, Mugs, and More! - Doctors without Borders",
        "description": "Check out my new store!  You can represent the Knights of Apollo and support Doctors without borders!  100% of the proceeds will go to charity!\n\nStore: https:\/\/teespring.com\/stores\/pixelated-apollo\n\nDoctors without Borders: https:\/\/donate.doctorswithoutborders.org\/onetime-b.cfm?source=ADD170U0U01&utm_source=AdWords&utm_medium=ppc&utm_campaign=GooglePaid&utm_content=brand\n\nIf you enjoyed the video don't forget to Like and Leave a comment :D\n\n-----------------------------------------PA Merchandise----------------------------------------------\n\nBUYING A SHIRT WILL SUPPORT A CHARITY!\n\nRepresent the Knight's of Apollo!\nBuy a T-shirt Here: Coming Soon!\n\n----------------------------------How You Can Support Me! -----------------------------------\n\n- Like, share and leave a comment :D\n- Turn OFF adblock or whitelist my channel\n- Send me a GREAT battle Replay: pixelatedapollo@gmail.com\n\n------------------------------------------Connect With Me!-----------------------------------------\n\n- Email: pixelatedapollo@gmail.com\n- Twitter: https:\/\/twitter.com\/PixelatedApollo\n- Steam Group:  http:\/\/steamcommunity.com\/groups\/apollosknights\n- Twitch: http:\/\/www.twitch.tv\/pixelatedapollo",
        "author": "Pixelated Apollo",
        "mediaDuration": 369,
        "prettyDuration": "00:06:09",
        "views": "10482"
    },
    "transcripts": "",
    "metrics_statistics": ""
}