{
    "title": "Let's Play Total War: Rome 2 - Epirus - Episode 19",
    "description": "Part 19 of this epic store :P\n\nEnjoy!",
    "referenceId": "JCE0fepWfHY",
    "date_created": "1401722921",
    "date_modified": "1506478303",
    "tags": "",
    "sourceId": "4",
    "status": "approved",
    "visibility": "1",
    "VV_VI": null,
    "engagement_score": null,
    "conversion_score": null,
    "CVV_VI": null,
    "id": "117406038",
    "loginId": "1759034",
    "entityType": "1",
    "titleTextEncoded": "Let-s-Play-Total-War-Rome-2-Epirus-Episode-19",
    "category": "",
    "tvp_profiles": [
        "32",
        "25"
    ],
    "tvp_profiles_manual": "",
    "tvp_profiles_maxscore": 136.33907,
    "VIDEO_LENGTH": "LONG",
    "duration": 2667,
    "settings": "",
    "asset": {
        "type": "youtube",
        "thumbnailUrl": "https:\/\/i.ytimg.com\/vi\/JCE0fepWfHY\/maxresdefault.jpg",
        "uploadDate": 1401722921,
        "videoId": "JCE0fepWfHY",
        "title": "Let's Play Total War: Rome 2 - Epirus - Episode 19",
        "description": "Part 19 of this epic store :P\n\nEnjoy!",
        "author": "Pixelated Apollo",
        "mediaDuration": 2667,
        "prettyDuration": "00:44:27",
        "views": "1866"
    },
    "transcripts": "",
    "metrics_statistics": ""
}