{
    "title": "Total War: Rome 2 Online Battle #12 (2v2)- Freddy Smith!",
    "description": "A 2v2 I play as Athens!\n\nEnjoy!",
    "referenceId": "WhPmWsOCFSs",
    "date_created": "1402765204",
    "date_modified": "1506478302",
    "tags": "",
    "sourceId": "4",
    "status": "approved",
    "visibility": "1",
    "VV_VI": null,
    "engagement_score": null,
    "conversion_score": null,
    "CVV_VI": null,
    "id": "117406024",
    "loginId": "1759034",
    "entityType": "1",
    "titleTextEncoded": "Total-War-Rome-2-Online-Battle-12-2v2-Freddy-Smith",
    "category": "",
    "tvp_profiles": [
        "32"
    ],
    "tvp_profiles_manual": "",
    "tvp_profiles_maxscore": 136.8386,
    "VIDEO_LENGTH": "LONG",
    "duration": 765,
    "settings": "",
    "asset": {
        "type": "youtube",
        "thumbnailUrl": "https:\/\/i.ytimg.com\/vi\/WhPmWsOCFSs\/maxresdefault.jpg",
        "uploadDate": 1402765204,
        "videoId": "WhPmWsOCFSs",
        "title": "Total War: Rome 2 Online Battle #12 (2v2)- Freddy Smith!",
        "description": "A 2v2 I play as Athens!\n\nEnjoy!",
        "author": "Pixelated Apollo",
        "mediaDuration": 765,
        "prettyDuration": "00:12:45",
        "views": "2709"
    },
    "transcripts": "",
    "metrics_statistics": ""
}