{
    "title": "MASSIVE NAVAL BATTLE - Napoleon Total War - Darth Mod Gameplay",
    "description": "MASSIVE NAVAL BATTLE - Napoleon Total War - Darth Mod Gameplay - Today we are going to set sail in an epic battle. Today we are playing a naval battle in Napoleon Total War Darth Mod. Jackiefish will be joining me as the United Kingdoms, and I play as Portugal. We face a combined force of Ottomans and French. Enjoy the Naval Battle! :D\n\nSultan's Channel: https:\/\/www.youtube.com\/channel\/UCnbVfcV2QNdg2ApY12-AgZQ\n\nJackie's Channel: https:\/\/www.youtube.com\/user\/Jackiefishhhhhh\n\nDarth Mod: http:\/\/www.moddb.com\/mods\/darthmod-napoleon\n\nJOIN MY DISCORD SERVER: https:\/\/discord.gg\/JjR7UR3\n\nIf you enjoyed the video don't forget to Like and Leave a comment :D\n\n-----------------------------------------PA Merchandise---------------------------------------------\n\nBUYING A SHIRT WILL SUPPORT A CHARITY!\n\nRepresent the Knight's of Apollo!\nBuy a T-shirt Here: https:\/\/teespring.com\/stores\/pixelated-apollo\n\n----------------------------------How You Can Support Me! -----------------------------------\n\n- Like, share and leave a comment :D\n- Turn OFF adblock or whitelist my channel\n- Send me a GREAT battle Replay: pixelatedapollo@gmail.com\n- Purchase a Server at: https:\/\/oasis-hosting.net\/ and use this discount code - PA2017 \n\n------------------------------------------Connect With Me!-----------------------------------------\n\n- Email: pixelatedapollo@gmail.com\n- Twitter: https:\/\/twitter.com\/PixelatedApollo\n- Steam Group:  http:\/\/steamcommunity.com\/groups\/apollosknights\n- Twitch: http:\/\/www.twitch.tv\/pixelatedapollo",
    "referenceId": "kgMEXLAcgsE",
    "date_created": "1500127205",
    "date_modified": "1506478185",
    "tags": "",
    "sourceId": "4",
    "status": "approved",
    "visibility": "1",
    "VV_VI": null,
    "engagement_score": null,
    "conversion_score": null,
    "CVV_VI": null,
    "id": "117404806",
    "loginId": "1759034",
    "entityType": "1",
    "titleTextEncoded": "MASSIVE-NAVAL-BATTLE-Napoleon-Total-War-Darth-Mod-Gameplay",
    "category": "",
    "tvp_profiles": [
        "32",
        "18"
    ],
    "tvp_profiles_manual": "",
    "tvp_profiles_maxscore": 1253.3938,
    "VIDEO_LENGTH": "LONG",
    "duration": 2367,
    "settings": "",
    "asset": {
        "type": "youtube",
        "thumbnailUrl": "https:\/\/i.ytimg.com\/vi\/kgMEXLAcgsE\/maxresdefault.jpg",
        "uploadDate": 1500127205,
        "videoId": "kgMEXLAcgsE",
        "title": "MASSIVE NAVAL BATTLE - Napoleon Total War - Darth Mod Gameplay",
        "description": "MASSIVE NAVAL BATTLE - Napoleon Total War - Darth Mod Gameplay - Today we are going to set sail in an epic battle. Today we are playing a naval battle in Napoleon Total War Darth Mod. Jackiefish will be joining me as the United Kingdoms, and I play as Portugal. We face a combined force of Ottomans and French. Enjoy the Naval Battle! :D\n\nSultan's Channel: https:\/\/www.youtube.com\/channel\/UCnbVfcV2QNdg2ApY12-AgZQ\n\nJackie's Channel: https:\/\/www.youtube.com\/user\/Jackiefishhhhhh\n\nDarth Mod: http:\/\/www.moddb.com\/mods\/darthmod-napoleon\n\nJOIN MY DISCORD SERVER: https:\/\/discord.gg\/JjR7UR3\n\nIf you enjoyed the video don't forget to Like and Leave a comment :D\n\n-----------------------------------------PA Merchandise---------------------------------------------\n\nBUYING A SHIRT WILL SUPPORT A CHARITY!\n\nRepresent the Knight's of Apollo!\nBuy a T-shirt Here: https:\/\/teespring.com\/stores\/pixelated-apollo\n\n----------------------------------How You Can Support Me! -----------------------------------\n\n- Like, share and leave a comment :D\n- Turn OFF adblock or whitelist my channel\n- Send me a GREAT battle Replay: pixelatedapollo@gmail.com\n- Purchase a Server at: https:\/\/oasis-hosting.net\/ and use this discount code - PA2017 \n\n------------------------------------------Connect With Me!-----------------------------------------\n\n- Email: pixelatedapollo@gmail.com\n- Twitter: https:\/\/twitter.com\/PixelatedApollo\n- Steam Group:  http:\/\/steamcommunity.com\/groups\/apollosknights\n- Twitch: http:\/\/www.twitch.tv\/pixelatedapollo",
        "author": "Pixelated Apollo",
        "mediaDuration": 2367,
        "prettyDuration": "00:39:27",
        "views": "141137"
    },
    "transcripts": "",
    "metrics_statistics": ""
}