{
    "title": "Uruk-Hai Grind  - Third Age Total War (2v3 Online Siege Battle #32)",
    "description": "Welcome back to Third Age Total War!  Today we are at Helms Deep, Arnor and the Dwarves are fighting for their lives.  3 armies are at their gates.  2 from Isengard and 1 from Harad.  Enjoy the fight!\n\nOh and you are going to need some snacks!  no better yet a whole meal!  :p\n_\nVisit my Website & Podcast!\n\nThanks to this awesome community I built a website for Total War fans, gamers, and history nerds.  It has blog posts, a Podcast, and a forum.  \n\nTotal War Tavern (Website): http:\/\/totalwartavern.com\/\n\nThe Round Table (Podcast-itunes): https:\/\/itunes.apple.com\/us\/podcast\/round-table-total-war-gaming\/id1012071205?mt=2\n\n*Be sure to give the podcast 5 Stars :D\n-------------------------------------------------------------------------------------------------------------\n\nHow to send me Battle Replays!\n\nThis video will show you how to send me battle replays :D https:\/\/www.youtube.com\/watch?v=7nG3uZoDkCU\n-------------------------------------------------------------------------------------------------------------\n\nHow to play Medieval 2 Total War & Rome Total War Online!\n\nGamespy Servers are down, but there is still hope.  Thanks to CA and steam you can still play the game online\n\nHow to play Online: https:\/\/www.youtube.com\/watch?v=YGfItCMitPg\n-------------------------------------------------------------------------------------------------------------\n\nWhy do I block out the Mini-Map with annotations for Sub battle replays?\n\nI block it out because the Mini-Map gives away who sent in the battle replay.  And in most cases whoever sends in the battle replay wins the battle.  So I block it to keep it a surprise :D  \n\n_\n\nConnect With me!\n\nEmail: pixelatedapollo@gmail.com\nTwitter: https:\/\/twitter.com\/PixelatedApollo\nSteam Group:  http:\/\/steamcommunity.com\/groups\/apollosknights\nTwitch: http:\/\/www.twitch.tv\/pixelatedapollo\nTeamSpeak: thewarcamp.vortexservers.com:10124",
    "referenceId": "GT80hicSLmU",
    "date_created": "1453131475",
    "date_modified": "1506478241",
    "tags": "",
    "sourceId": "4",
    "status": "approved",
    "visibility": "1",
    "VV_VI": null,
    "engagement_score": null,
    "conversion_score": null,
    "CVV_VI": null,
    "id": "117405355",
    "loginId": "1759034",
    "entityType": "1",
    "titleTextEncoded": "Uruk-Hai-Grind-Third-Age-Total-War-2v3-Online-Siege-Battle-32",
    "category": "",
    "tvp_profiles": [
        "25",
        "11"
    ],
    "tvp_profiles_manual": "",
    "tvp_profiles_maxscore": 2131.6042,
    "VIDEO_LENGTH": "LONG",
    "duration": 4075,
    "settings": "",
    "asset": {
        "type": "youtube",
        "thumbnailUrl": "https:\/\/i.ytimg.com\/vi\/GT80hicSLmU\/maxresdefault.jpg",
        "uploadDate": 1453131475,
        "videoId": "GT80hicSLmU",
        "title": "Uruk-Hai Grind  - Third Age Total War (2v3 Online Siege Battle #32)",
        "description": "Welcome back to Third Age Total War!  Today we are at Helms Deep, Arnor and the Dwarves are fighting for their lives.  3 armies are at their gates.  2 from Isengard and 1 from Harad.  Enjoy the fight!\n\nOh and you are going to need some snacks!  no better yet a whole meal!  :p\n_\nVisit my Website & Podcast!\n\nThanks to this awesome community I built a website for Total War fans, gamers, and history nerds.  It has blog posts, a Podcast, and a forum.  \n\nTotal War Tavern (Website): http:\/\/totalwartavern.com\/\n\nThe Round Table (Podcast-itunes): https:\/\/itunes.apple.com\/us\/podcast\/round-table-total-war-gaming\/id1012071205?mt=2\n\n*Be sure to give the podcast 5 Stars :D\n-------------------------------------------------------------------------------------------------------------\n\nHow to send me Battle Replays!\n\nThis video will show you how to send me battle replays :D https:\/\/www.youtube.com\/watch?v=7nG3uZoDkCU\n-------------------------------------------------------------------------------------------------------------\n\nHow to play Medieval 2 Total War & Rome Total War Online!\n\nGamespy Servers are down, but there is still hope.  Thanks to CA and steam you can still play the game online\n\nHow to play Online: https:\/\/www.youtube.com\/watch?v=YGfItCMitPg\n-------------------------------------------------------------------------------------------------------------\n\nWhy do I block out the Mini-Map with annotations for Sub battle replays?\n\nI block it out because the Mini-Map gives away who sent in the battle replay.  And in most cases whoever sends in the battle replay wins the battle.  So I block it to keep it a surprise :D  \n\n_\n\nConnect With me!\n\nEmail: pixelatedapollo@gmail.com\nTwitter: https:\/\/twitter.com\/PixelatedApollo\nSteam Group:  http:\/\/steamcommunity.com\/groups\/apollosknights\nTwitch: http:\/\/www.twitch.tv\/pixelatedapollo\nTeamSpeak: thewarcamp.vortexservers.com:10124",
        "author": "Pixelated Apollo",
        "mediaDuration": 4075,
        "prettyDuration": "01:07:55",
        "views": "204891"
    },
    "transcripts": "",
    "metrics_statistics": ""
}